wyoming_kokoro_torch/__init__.py
wyoming_kokoro_torch/__main__.py
wyoming_kokoro_torch/download.py
wyoming_kokoro_torch/handler.py
wyoming_kokoro_torch/voices.json
wyoming_kokoro_torch-3.2.0.dist-info/licenses/LICENSE.md
wyoming_kokoro_torch-3.2.0.dist-info/METADATA
wyoming_kokoro_torch-3.2.0.dist-info/WHEEL
wyoming_kokoro_torch-3.2.0.dist-info/entry_points.txt
wyoming_kokoro_torch-3.2.0.dist-info/top_level.txt
wyoming_kokoro_torch-3.2.0.dist-info/RECORD
