Metadata-Version: 2.4
Name: wyoming-kokoro-torch
Version: 3.2.0
Summary: Wyoming Server for Kokoro Torch
Author-email: Laurent Debacker <debackerl@gmail.com>
License: MIT
Project-URL: Homepage, http://github.com/debackerl/wyoming-kokoro-torch
Keywords: rhasspy,wyoming,kokoro,tts
Classifier: Development Status :: 3 - Alpha
Classifier: Intended Audience :: Developers
Classifier: Topic :: Text Processing :: Linguistic
Classifier: Programming Language :: Python :: 3.8
Classifier: Programming Language :: Python :: 3.9
Classifier: Programming Language :: Python :: 3.10
Classifier: Programming Language :: Python :: 3.11
Classifier: Programming Language :: Python :: 3.12
Classifier: Programming Language :: Python :: 3.13
Requires-Python: >=3.8
License-File: LICENSE.md
Requires-Dist: wyoming<1.8,>=1.7.2
Requires-Dist: kokoro==0.9.4
Requires-Dist: sentence-stream==1.2.0
Provides-Extra: dev
Requires-Dist: black==24.8.0; extra == "dev"
Requires-Dist: flake8==7.1.1; extra == "dev"
Requires-Dist: mypy==1.14.0; extra == "dev"
Requires-Dist: pylint==3.2.7; extra == "dev"
Requires-Dist: pytest==8.3.4; extra == "dev"
Requires-Dist: pytest-asyncio==1.1.0; extra == "dev"
Requires-Dist: build==1.2.2; extra == "dev"
Requires-Dist: scipy<2,>=1.10; extra == "dev"
Requires-Dist: numpy<2,>=1.20; extra == "dev"
Requires-Dist: python-speech-features==0.6; extra == "dev"
Requires-Dist: twine==6.1.0; extra == "dev"
Dynamic: license-file
